fuse.py
fuse_python.libs/libfuse-8b10bc30.so.2.9.7
fuse_python-1.0.7.dist-info/AUTHORS
fuse_python-1.0.7.dist-info/COPYING
fuse_python-1.0.7.dist-info/WHEEL
fuse_python-1.0.7.dist-info/METADATA
fuse_python-1.0.7.dist-info/RECORD
fuse_python-1.0.7.dist-info/top_level.txt
fuseparts/subbedopts.py
fuseparts/__init__.py
fuseparts/_fuse.cpython-312-x86_64-linux-gnu.so
fuseparts/setcompatwrap.py
