Metadata-Version: 2.1
Name: fuse-python
Version: 1.0.7
Summary: Bindings for FUSE
Home-page: https://github.com/libfuse/python-fuse
Author: Jeff Epler <jepler@unpythonic.dhs.org>, Csaba Henk <csaba.henk@creo.hu>, Steven James, Miklos Szeredi <miklos@szeredi.hu>, Sébastien Delafond<sdelafond@gmail.com>
Maintainer: Sébastien Delafond
Maintainer-email: sdelafond@gmail.com
License: LGPL
Platform: posix
Classifier: Development Status :: 5 - Production/Stable
Classifier: Intended Audience :: Developers
Classifier: License :: OSI Approved :: GNU Library or Lesser General Public License (LGPL)
Classifier: Environment :: Console
Classifier: Operating System :: POSIX
Classifier: Programming Language :: C
Classifier: Programming Language :: Python
Classifier: Programming Language :: Python :: 2
Classifier: Programming Language :: Python :: 2.7
Classifier: Programming Language :: Python :: 3
Classifier: Programming Language :: Python :: 3.5
Classifier: Programming Language :: Python :: 3.6
Classifier: Programming Language :: Python :: 3.7
Classifier: Programming Language :: Python :: 3.8
Classifier: Programming Language :: Python :: 3.9
Classifier: Programming Language :: Python :: 3.10
Classifier: Programming Language :: Python :: 3.11
Classifier: Programming Language :: Python :: 3.12
Classifier: Topic :: System :: Filesystems
License-File: COPYING
License-File: AUTHORS
